llm_knowledge/__init__.py
llm_knowledge/epistemic_diversity.py
llm_knowledge/generate.py
llm_knowledge/model.py
llm_knowledge/prompts/epistemic_diversity/baseline_extraction_prompt.txt
llm_knowledge/prompts/epistemic_diversity/factoid_extraction_prompt.txt
llm_knowledge/prompts/epistemic_diversity/factoid_extraction_prompt_no_context.txt
llm_knowledge/prompts/epistemic_diversity/multilingual/decomposition/ar.txt
llm_knowledge/prompts/epistemic_diversity/multilingual/decomposition/de.txt
llm_knowledge/prompts/epistemic_diversity/multilingual/decomposition/en.txt
llm_knowledge/prompts/epistemic_diversity/multilingual/decomposition/es.txt
llm_knowledge/prompts/epistemic_diversity/multilingual/decomposition/fr.txt
llm_knowledge/prompts/epistemic_diversity/multilingual/decomposition/hi.txt
llm_knowledge/prompts/epistemic_diversity/multilingual/decomposition/ko.txt
llm_knowledge/prompts/epistemic_diversity/multilingual/decomposition/pt.txt
llm_knowledge/prompts/epistemic_diversity/multilingual/decomposition/ru.txt
llm_knowledge/prompts/epistemic_diversity/multilingual/decomposition/zh.txt
llm_knowledge/prompts/epistemic_diversity/multilingual/matching/en.txt
llm_knowledge/util/__init__.py
llm_knowledge/util/helpers.py
llm_knowledge-0.1.2.dist-info/licenses/LICENSE
llm_knowledge-0.1.2.dist-info/METADATA
llm_knowledge-0.1.2.dist-info/WHEEL
llm_knowledge-0.1.2.dist-info/top_level.txt
llm_knowledge-0.1.2.dist-info/RECORD
