Metadata-Version: 2.4
Name: llm_knowledge
Version: 0.1.2
Summary: Tools to extract, visualize, and quantify latent knowledge in large language models
Author-email: Dustin Wright <dw@di.ku.dk>
Project-URL: Homepage, https://github.com/dwright37/llm-knowledge
Project-URL: Issues, https://github.com/dwright37/llm-knowledge/issues
Classifier: Programming Language :: Python :: 3
Classifier: Operating System :: OS Independent
Classifier: License :: OSI Approved :: MIT License
Requires-Python: >=3.9
License-File: LICENSE
Requires-Dist: pandas
Requires-Dist: bitsandbytes
Requires-Dist: matplotlib
Requires-Dist: pyarrow
Requires-Dist: seaborn
Requires-Dist: tqdm
Requires-Dist: nltk
Requires-Dist: datasets
Requires-Dist: spacy
Requires-Dist: scikit-learn
Requires-Dist: sentence-transformers
Requires-Dist: openai
Dynamic: license-file
